sttp/__init__.py
sttp/errors.py
sttp/parser.py
sttp/pkg_meta.py
sttp/utils.py
sttp/core/__init__.py
sttp/core/functions.py
sttp/core/match_funs.py
sttp/core/matches.py
sttp/ext/__init__.py
sttp/ext/function.py
sttp/ext/match.py
sttp/ext/match_fun.py
sttp/ext/register.py
sttp/subst/__init__.py
sttp/subst/grammar.txt
sttp/subst/handler.py
sttp/subst/parser.py
sttp-0.0.3.dist-info/LICENSE
sttp-0.0.3.dist-info/METADATA
sttp-0.0.3.dist-info/WHEEL
sttp-0.0.3.dist-info/entry_points.txt
sttp-0.0.3.dist-info/top_level.txt
sttp-0.0.3.dist-info/RECORD
