Metadata-Version: 2.1
Name: sttp
Version: 0.0.3
Summary: Strict Text Template Parsing
Home-page: https://github.com/mwri/sttp
Author: Michael Wright
Author-email: mjw@methodanalysis.com
License: UNKNOWN
Platform: UNKNOWN
Classifier: Programming Language :: Python :: 3
Classifier: License :: OSI Approved :: MIT License
Classifier: Operating System :: OS Independent
Requires-Python: >=3.6
Requires-Dist: lark (==1.1.2)
Provides-Extra: dev
Requires-Dist: Sphinx (==4.4.0) ; extra == 'dev'
Requires-Dist: black (==22.1.0) ; extra == 'dev'
Requires-Dist: coverage (==6.3.2) ; extra == 'dev'
Requires-Dist: lark (==1.1.2) ; extra == 'dev'
Requires-Dist: pytest-mock (==3.7.0) ; extra == 'dev'
Requires-Dist: pytest (==7.1.0) ; extra == 'dev'
Requires-Dist: sphinx-rtd-theme (==1.0.0) ; extra == 'dev'
